{"is_source_file": true, "format": "JavaScript (React JSX)", "description": "Main React component for a Candy Pop styled To-Do List app, implementing task management, theme toggling, filtering, and UI elements.", "external_files": ["./App.css"], "external_methods": ["React.useState", "React.useEffect", "React.useMemo"], "published": ["App"], "classes": [], "methods": [{"name": "App()", "description": "Main application component managing theme, tasks, and UI interactions.", "scope": "", "scopeKind": ""}, {"name": "CandyBackground()", "description": "Decorative background component with colorful blobs.", "scope": "", "scopeKind": ""}, {"name": "FilterPills({ filter, setFilter })", "description": "Component for filtering tasks (all, active, done).", "scope": "", "scopeKind": ""}, {"name": "TaskInput({ onAdd })", "description": "Input component for adding new tasks.", "scope": "", "scopeKind": ""}, {"name": "TaskList({ tasks, onToggle, onDelete, onUpdate })", "description": "Component rendering the list of task items.", "scope": "TaskInput", "scopeKind": "function"}, {"name": "TaskItem({ task, onToggle, onDelete, onUpdate })", "description": "Component representing a single task with editing, toggling, and deleting capabilities.", "scope": "TaskInput", "scopeKind": "function"}, {"name": "AppMeta()", "description": "Footer component with metadata info.", "scope": "TaskInput", "scopeKind": "function"}], "calls": ["React.useState", "React.useEffect", "React.useMemo", "setTheme", "setTasks", "setFilter", "uid", "document.documentElement.setAttribute", "setTasks", "setTasks", "setTasks", "setTasks", "setTasks"], "search-terms": ["React", "Candy Pop To-Do", "task filtering", "theme toggling", "task CRUD", "styled components", "react hooks", "task list", "task editing"], "state": 2, "file_id": 11, "knowledge_revision": 24, "git_revision": "61e967694f44a9d99257512fbb0355c3f8269bec", "revision_history": [{"23": "61e967694f44a9d99257512fbb0355c3f8269bec"}, {"24": "61e967694f44a9d99257512fbb0355c3f8269bec"}], "ctags": [{"_type": "tag", "name": "App", "path": "/home/kavia/workspace/code-generation/simple-to-do-list-app-167266-167275/react_frontend/src/App.js", "pattern": "/^function App() {$/", "language": "JavaScript", "kind": "function", "signature": "()"}, {"_type": "tag", "name": "AppMeta", "path": "/home/kavia/workspace/code-generation/simple-to-do-list-app-167266-167275/react_frontend/src/App.js", "pattern": "/^function AppMeta() {$/", "language": "JavaScript", "kind": "function", "signature": "()", "scope": "TaskInput", "scopeKind": "function"}, {"_type": "tag", "name": "CandyBackground", "path": "/home/kavia/workspace/code-generation/simple-to-do-list-app-167266-167275/react_frontend/src/App.js", "pattern": "/^function CandyBackground() {$/", "language": "JavaScript", "kind": "function", "signature": "()"}, {"_type": "tag", "name": "FilterPills", "path": "/home/kavia/workspace/code-generation/simple-to-do-list-app-167266-167275/react_frontend/src/App.js", "pattern": "/^function FilterPills({ filter, setFilter }) {$/", "language": "JavaScript", "kind": "function", "signature": "({ filter, setFilter })"}, {"_type": "tag", "name": "Switch to ${theme === 'light' ? 'dark' : 'light'} mode", "path": "/home/kavia/workspace/code-generation/simple-to-do-list-app-167266-167275/react_frontend/src/App.js", "pattern": "/^              aria-label={`Switch to ${theme === 'light' ? 'dark' : 'light'} mode`}$/", "language": "JavaScript", "kind": "field", "scope": "App.aria", "scopeKind": "class"}, {"_type": "tag", "name": "TaskInput", "path": "/home/kavia/workspace/code-generation/simple-to-do-list-app-167266-167275/react_frontend/src/App.js", "pattern": "/^function TaskInput({ onAdd }) {$/", "language": "JavaScript", "kind": "function", "signature": "({ onAdd })"}, {"_type": "tag", "name": "TaskItem", "path": "/home/kavia/workspace/code-generation/simple-to-do-list-app-167266-167275/react_frontend/src/App.js", "pattern": "/^function TaskItem({ task, onToggle, onDelete, onUpdate }) {$/", "language": "JavaScript", "kind": "function", "signature": "({ task, onToggle, onDelete, onUpdate })", "scope": "TaskInput", "scopeKind": "function"}, {"_type": "tag", "name": "TaskList", "path": "/home/kavia/workspace/code-generation/simple-to-do-list-app-167266-167275/react_frontend/src/App.js", "pattern": "/^function TaskList({ tasks, onToggle, onDelete, onUpdate }) {$/", "language": "JavaScript", "kind": "function", "signature": "({ tasks, onToggle, onDelete, onUpdate })", "scope": "TaskInput", "scopeKind": "function"}, {"_type": "tag", "name": "completed ? 'active' : 'done'}", "path": "/home/kavia/workspace/code-generation/simple-to-do-list-app-167266-167275/react_frontend/src/App.js", "pattern": "/^          aria-label={`Mark \"${task.text}\" as ${task.completed ? 'active' : 'done'}`}$/", "language": "JavaScript", "kind": "field", "scope": "TaskInput.TaskItem.aria.Mark \"${task.text}\" as ${task", "scopeKind": "class"}, {"_type": "tag", "name": "completed ? 'done' : ''}", "path": "/home/kavia/workspace/code-generation/simple-to-do-list-app-167266-167275/react_frontend/src/App.js", "pattern": "/^    <li className={`task-item ${task.completed ? 'done' : ''}`}>$/", "language": "JavaScript", "kind": "field", "scope": "TaskInput.TaskItem.AnonymousClassa34aac1a0101.task-item ${task", "scopeKind": "class"}, {"_type": "tag", "name": "completed", "path": "/home/kavia/workspace/code-generation/simple-to-do-list-app-167266-167275/react_frontend/src/App.js", "pattern": "/^    const newTask = { id: uid(), text: text.trim(), completed: false, createdAt: Date.now() };$/", "language": "JavaScript", "kind": "property", "scope": "App.newTask", "scopeKind": "class"}, {"_type": "tag", "name": "createdAt", "path": "/home/kavia/workspace/code-generation/simple-to-do-list-app-167266-167275/react_frontend/src/App.js", "pattern": "/^    const newTask = { id: uid(), text: text.trim(), completed: false, createdAt: Date.now() };$/", "language": "JavaScript", "kind": "property", "scope": "App.newTask", "scopeKind": "class"}, {"_type": "tag", "name": "editing", "path": "/home/kavia/workspace/code-generation/simple-to-do-list-app-167266-167275/react_frontend/src/App.js", "pattern": "/^          aria-label={editing ? 'Save' : 'Edit'}$/", "language": "JavaScript", "kind": "field", "scope": "TaskInput.TaskItem.aria", "scopeKind": "class"}, {"_type": "tag", "name": "editing", "path": "/home/kavia/workspace/code-generation/simple-to-do-list-app-167266-167275/react_frontend/src/App.js", "pattern": "/^          title={editing ? 'Save' : 'Edit'}$/", "language": "JavaScript", "kind": "field", "scope": "TaskInput.TaskItem.title", "scopeKind": "class"}, {"_type": "tag", "name": "filteredTasks", "path": "/home/kavia/workspace/code-generation/simple-to-do-list-app-167266-167275/react_frontend/src/App.js", "pattern": "/^            tasks={filteredTasks}$/", "language": "JavaScript", "kind": "field", "scope": "App.tasks", "scopeKind": "class"}, {"_type": "tag", "name": "handleDelete", "path": "/home/kavia/workspace/code-generation/simple-to-do-list-app-167266-167275/react_frontend/src/App.js", "pattern": "/^            onDelete={handleDelete}$/", "language": "JavaScript", "kind": "field", "scope": "App.onDelete", "scopeKind": "class"}, {"_type": "tag", "name": "handleToggle", "path": "/home/kavia/workspace/code-generation/simple-to-do-list-app-167266-167275/react_frontend/src/App.js", "pattern": "/^            onToggle={handleToggle}$/", "language": "JavaScript", "kind": "field", "scope": "App.onToggle", "scopeKind": "class"}, {"_type": "tag", "name": "handleUpdate", "path": "/home/kavia/workspace/code-generation/simple-to-do-list-app-167266-167275/react_frontend/src/App.js", "pattern": "/^            onUpdate={handleUpdate}$/", "language": "JavaScript", "kind": "field", "scope": "App.onUpdate", "scopeKind": "class"}, {"_type": "tag", "name": "id", "path": "/home/kavia/workspace/code-generation/simple-to-do-list-app-167266-167275/react_frontend/src/App.js", "pattern": "/^    const newTask = { id: uid(), text: text.trim(), completed: false, createdAt: Date.now() };$/", "language": "JavaScript", "kind": "property", "scope": "App.newTask", "scopeKind": "class"}, {"_type": "tag", "name": "newTask", "path": "/home/kavia/workspace/code-generation/simple-to-do-list-app-167266-167275/react_frontend/src/App.js", "pattern": "/^    const newTask = { id: uid(), text: text.trim(), completed: false, createdAt: Date.now() };$/", "language": "JavaScript", "kind": "class", "scope": "App", "scopeKind": "class"}, {"_type": "tag", "name": "onDelete", "path": "/home/kavia/workspace/code-generation/simple-to-do-list-app-167266-167275/react_frontend/src/App.js", "pattern": "/^          onClick={onDelete}$/", "language": "JavaScript", "kind": "field", "scope": "TaskInput.TaskItem.onClick", "scopeKind": "class"}, {"_type": "tag", "name": "onToggle", "path": "/home/kavia/workspace/code-generation/simple-to-do-list-app-167266-167275/react_frontend/src/App.js", "pattern": "/^          onChange={onToggle}$/", "language": "JavaScript", "kind": "field", "scope": "TaskInput.TaskItem.onChange", "scopeKind": "class"}, {"_type": "tag", "name": "task", "path": "/home/kavia/workspace/code-generation/simple-to-do-list-app-167266-167275/react_frontend/src/App.js", "pattern": "/^          checked={task.completed}$/", "language": "JavaScript", "kind": "field", "scope": "TaskInput.TaskItem.checked", "scopeKind": "class"}, {"_type": "tag", "name": "text", "path": "/home/kavia/workspace/code-generation/simple-to-do-list-app-167266-167275/react_frontend/src/App.js", "pattern": "/^          value={text}$/", "language": "JavaScript", "kind": "field", "scope": "TaskInput.value", "scopeKind": "class"}, {"_type": "tag", "name": "text", "path": "/home/kavia/workspace/code-generation/simple-to-do-list-app-167266-167275/react_frontend/src/App.js", "pattern": "/^    const newTask = { id: uid(), text: text.trim(), completed: false, createdAt: Date.now() };$/", "language": "JavaScript", "kind": "property", "scope": "App.newTask", "scopeKind": "class"}, {"_type": "tag", "name": "toggleTheme", "path": "/home/kavia/workspace/code-generation/simple-to-do-list-app-167266-167275/react_frontend/src/App.js", "pattern": "/^              onClick={toggleTheme}$/", "language": "JavaScript", "kind": "field", "scope": "App.onClick", "scopeKind": "class"}, {"_type": "tag", "name": "uid", "path": "/home/kavia/workspace/code-generation/simple-to-do-list-app-167266-167275/react_frontend/src/App.js", "pattern": "/^const uid = () => Math.random().toString(36).slice(2) + Date.now().toString(36);$/", "language": "JavaScript", "kind": "constant"}], "hash": "28739ebbf5ee0211aaeba20682938f3f", "format-version": 4, "code-base-name": "react_frontend", "filename": "react_frontend/src/App.js", "fields": [{"name": "aria-label={`Switch to ${theme === 'light' ? 'dark' : 'light'} mode`}", "scope": "App.aria", "scopeKind": "class", "description": "unavailable"}, {"name": "aria-label={`Mark \"${task.text}\" as ${task.completed ? 'active' : 'done'}`}", "scope": "TaskInput.TaskItem.aria.Mark \"${task.text}\" as ${task", "scopeKind": "class", "description": "unavailable"}, {"name": "<li className={`task-item ${task.completed ? 'done' : ''}`}>", "scope": "TaskInput.TaskItem.AnonymousClassa34aac1a0101.task-item ${task", "scopeKind": "class", "description": "unavailable"}, {"name": "const newTask = { id: uid(), text: text.trim(), completed: false, createdAt: Date.now() };", "scope": "App.newTask", "scopeKind": "class", "description": "unavailable"}, {"name": "aria-label={editing ? 'Save' : 'Edit'}", "scope": "TaskInput.TaskItem.aria", "scopeKind": "class", "description": "unavailable"}, {"name": "title={editing ? 'Save' : 'Edit'}", "scope": "TaskInput.TaskItem.title", "scopeKind": "class", "description": "unavailable"}, {"name": "tasks={filteredTasks}", "scope": "App.tasks", "scopeKind": "class", "description": "unavailable"}, {"name": "onDelete={handleDelete}", "scope": "App.onDelete", "scopeKind": "class", "description": "unavailable"}, {"name": "onToggle={handleToggle}", "scope": "App.onToggle", "scopeKind": "class", "description": "unavailable"}, {"name": "onUpdate={handleUpdate}", "scope": "App.onUpdate", "scopeKind": "class", "description": "unavailable"}, {"name": "onClick={onDelete}", "scope": "TaskInput.TaskItem.onClick", "scopeKind": "class", "description": "unavailable"}, {"name": "onChange={onToggle}", "scope": "TaskInput.TaskItem.onChange", "scopeKind": "class", "description": "unavailable"}, {"name": "checked={task.completed}", "scope": "TaskInput.TaskItem.checked", "scopeKind": "class", "description": "unavailable"}, {"name": "value={text}", "scope": "TaskInput.value", "scopeKind": "class", "description": "unavailable"}, {"name": "onClick={toggleTheme}", "scope": "App.onClick", "scopeKind": "class", "description": "unavailable"}]}